AUTHORS
LICENSE
MANIFEST.in
README.md
requirements.txt
setup.cfg
setup.py
aclhound/__init__.py
aclhound/aclsemantics.py
aclhound/cli.py
aclhound/deploy.py
aclhound/generate.py
aclhound/license.py
aclhound/parser.py
aclhound/render.py
aclhound/textfsm.py
aclhound.egg-info/PKG-INFO
aclhound.egg-info/SOURCES.txt
aclhound.egg-info/dependency_links.txt
aclhound.egg-info/entry_points.txt
aclhound.egg-info/pbr.json
aclhound.egg-info/top_level.txt
aclhound/doc/__init__.py
aclhound/doc/aclhound.7
aclhound/doc/aclhound.conf.dist
aclhound/doc/grammar.ebnf
aclhound/targets/__init__.py
aclhound/targets/asa.py
aclhound/targets/deploy_asa.py
aclhound/targets/deploy_ios.py
aclhound/targets/ios.py
aclhound/targets/junos.py