Metadata-Version: 1.1
Name: aclhound
Version: 1.8.2
Summary: ACL Compiler
Home-page: https://github.com/job/aclhound
Author: Job Snijders
Author-email: job@instituut.net
License: BSD 2-Clause
Keywords: acl python ciscoasa ciscoios routing networking
Platform: UNKNOWN
Classifier: Intended Audience :: Developers
Classifier: Topic :: Software Development :: Libraries :: Python Modules
Classifier: Topic :: System :: Networking
Classifier: License :: OSI Approved :: BSD License
Classifier: Programming Language :: Python :: 2.7
